GozargahNodeBridge/__init__.py
GozargahNodeBridge/abstract_node.py
GozargahNodeBridge/controller.py
GozargahNodeBridge/grpclib.py
GozargahNodeBridge/rest.py
GozargahNodeBridge/utils.py
GozargahNodeBridge/common/service.proto
GozargahNodeBridge/common/service_grpc.py
GozargahNodeBridge/common/service_pb2.py
GozargahNodeBridge/common/service_pb2.pyi
gozargah_node_bridge-0.0.44.dist-info/METADATA
gozargah_node_bridge-0.0.44.dist-info/WHEEL
gozargah_node_bridge-0.0.44.dist-info/licenses/LICENSE
gozargah_node_bridge-0.0.44.dist-info/RECORD
