Metadata-Version: 2.4
Name: gozargah-node-bridge
Version: 0.0.44
Summary: python package to connect your project with gozargah node go
Project-URL: Homepage, https://github.com/m03ed/gozargah_node_bridge_py
Project-URL: Repository, https://github.com/m03ed/gozargah_node_bridge_py.git
License-File: LICENSE
Keywords: Gozargah,Gozargah-Node,Marzban,Marzban API,Marzban python
Classifier: Programming Language :: Python :: 3.12
Requires-Python: >=3.12
Requires-Dist: aiorwlock>=1.5.0
Requires-Dist: grpclib>=0.4.8
Requires-Dist: httpx>=0.28.1
Requires-Dist: protobuf>=6.31.1
